goodday_mcp/__init__.py
goodday_mcp/main.py
goodday_mcp-1.1.3.dist-info/METADATA
goodday_mcp-1.1.3.dist-info/WHEEL
goodday_mcp-1.1.3.dist-info/entry_points.txt
goodday_mcp-1.1.3.dist-info/licenses/LICENSE
goodday_mcp-1.1.3.dist-info/RECORD
