Metadata-Version: 2.4
Name: goodday-mcp
Version: 1.1.3
Summary: Model Context Protocol server for Goodday project management platform
Project-URL: Homepage, https://github.com/your-username/goodday-mcp
Project-URL: Documentation, https://github.com/your-username/goodday-mcp#readme
Project-URL: Repository, https://github.com/your-username/goodday-mcp.git
Project-URL: Issues, https://github.com/your-username/goodday-mcp/issues
Author-email: Roney <roney@goodday-mcp.dev>
License-Expression: MIT
License-File: LICENSE
Keywords: api,goodday,mcp,model-context-protocol,project-management,server
Classifier: Development Status :: 4 - Beta
Classifier: Intended Audience :: Developers
Classifier: License :: OSI Approved :: MIT License
Classifier: Operating System :: OS Independent
Classifier: Programming Language :: Python :: 3
Classifier: Programming Language :: Python :: 3.10
Classifier: Programming Language :: Python :: 3.11
Classifier: Programming Language :: Python :: 3.12
Classifier: Programming Language :: Python :: 3.13
Classifier: Topic :: Communications
Classifier: Topic :: Internet :: WWW/HTTP :: Dynamic Content
Classifier: Topic :: Office/Business :: Groupware
Classifier: Topic :: Software Development :: Libraries :: Python Modules
Requires-Python: >=3.10
Requires-Dist: httpx>=0.28.1
Requires-Dist: mcp>=1.9.4
